LICENSE
MANIFEST.in
README.md
setup.py
pybaywatch/TEX_forward.m
pybaywatch/UK_forward.m
pybaywatch/__init__.py
pybaywatch/bayfox_forward.m
pybaywatch/baymag_forward_ln.m
pybaywatch/baymbt_forward.m
pybaywatch/core.py
pybaywatch/fnval.m
pybaywatch/normrnd.m
pybaywatch/randsample.m
pybaywatch/rndcheck.m
pybaywatch/utils.py
pybaywatch/wrapper.py
pybaywatch.egg-info/PKG-INFO
pybaywatch.egg-info/SOURCES.txt
pybaywatch.egg-info/dependency_links.txt
pybaywatch.egg-info/not-zip-safe
pybaywatch.egg-info/requires.txt
pybaywatch.egg-info/top_level.txt