Metadata-Version: 2.1
Name: pybaywatch
Version: 2024.4.8
Summary: PyBAYWATCH: BAYWATCH in Python
Home-page: https://github.com/fzhu2e/pybaywatch
Author: Feng Zhu, Jessica Tierney
Author-email: fengzhu@ucar.edu, jesst@arizona.edu
License: MIT
Keywords: Bayeisan Hierarchical Proxy System Models for Sediments
Classifier: Programming Language :: Python :: 3.11
License-File: LICENSE
Requires-Dist: colorama
Requires-Dist: oct2py
